actionman/__init__.py
actionman/_format.py
actionman/env_var.py
actionman/exception.py
actionman/log.py
actionman/step_output.py
actionman/step_summary.py
actionman-0.1.1.dist-info/METADATA
actionman-0.1.1.dist-info/WHEEL
actionman-0.1.1.dist-info/top_level.txt
actionman-0.1.1.dist-info/RECORD
