Metadata-Version: 2.4
Name: ActionMan
Version: 0.1.1
Requires-Python: >=3.10
Requires-Dist: ProtocolMan<0.2,>=0.1
Requires-Dist: rich<14,>=13.8
